pytelegraf-0.2.0.dist-info/DESCRIPTION.rst
pytelegraf-0.2.0.dist-info/METADATA
pytelegraf-0.2.0.dist-info/RECORD
pytelegraf-0.2.0.dist-info/WHEEL
pytelegraf-0.2.0.dist-info/metadata.json
pytelegraf-0.2.0.dist-info/pbr.json
pytelegraf-0.2.0.dist-info/top_level.txt
telegraf/__init__.py
telegraf/client.py
telegraf/protocol.py
telegraf/tests.py
telegraf/utils.py
telegraf/defaults/__init__.py
telegraf/defaults/django.py
