Metadata-Version: 2.0
Name: pytelegraf
Version: 0.2.0
Summary: Telegraf client
Home-page: https://github.com/paksu/pytelegraf
Author: paksu
Author-email: UNKNOWN
License: MIT
Platform: UNKNOWN
Classifier: Environment :: Web Environment
Classifier: Intended Audience :: Developers
Classifier: License :: OSI Approved :: MIT License
Classifier: Operating System :: OS Independent
Classifier: Programming Language :: Python
Classifier: Programming Language :: Python :: 2.7
Classifier: Programming Language :: Python :: 3
Classifier: Programming Language :: Python :: 3.3
Classifier: Programming Language :: Python :: 3.4
Classifier: Programming Language :: Python :: 3.5
Provides-Extra: http
Requires-Dist: requests-futures (==0.9.7); extra == 'http'
